{
  "events": [
    {
      "id": 1,
      "name": "hhhhhtional de Carthage",
      "description": "Le lorem ipsum est, en imprimerie, une suite de mots sans signification utilisée à titre efefefpour calibrer une mise en page",
      "img": "event1.jpg",
      "price": 30,
      "nbTickets": 10,
      "nbParticipants": 10,
      "like": false
    },
    {
      "name": "thamer boukhris",
      "description": "dvdv",
      "price": "",
      "nbTickets": "",
      "img": "",
      "undefined": "",
      "id": 4
    }
  ]
}